{"lv":143,"height":7814.664462650539,"needBalls":15,"originHoles":[{"num":"10","radius":80,"x":0}],"holes":[{"num":"0","pos":{"x":-275,"y":-3543.811622341895},"radius":80},{"num":"15","pos":{"x":93,"y":-4892.747105334525},"radius":90},{"num":"0","pos":{"x":1,"y":-5675.13664447087},"radius":300}],"obstacles":[{"id":"17","position":{"x":3,"y":-7584}},{"id":"1","position":{"x":-45,"y":-239.64554293661348},"scaleX":-1},{"id":"1","position":{"x":46,"y":-332.6455429366135},"scaleX":-1},{"id":"1","position":{"x":46,"y":-425.6455429366135},"scaleX":-1},{"id":"1","position":{"x":46,"y":-518.6455429366135},"scaleX":-1},{"id":"1","position":{"x":-44,"y":-330.6455429366135},"scaleX":-1},{"id":"1","position":{"x":-44,"y":-421.6455429366135},"scaleX":-1},{"id":"1","position":{"x":-43,"y":-512.6455429366135},"scaleX":-1},{"id":"1","position":{"x":2,"y":-381.6455429366135},"scaleX":-0.64,"scaleY":0.64},{"id":"1","position":{"x":2,"y":-475.6455429366135},"scaleX":-0.64,"scaleY":0.64},{"id":"1","position":{"x":277,"y":-1400.3161653996626},"scaleX":2.96,"scaleY":2.99},{"id":"1","position":{"x":237,"y":-1548.3161653996626},"scaleX":2.96,"scaleY":2.99},{"id":"1","position":{"x":-237,"y":-1548.3161653996626},"scaleX":2.96,"scaleY":2.99},{"id":"1","position":{"x":-193,"y":-1696.3161653996626},"scaleX":2.96,"scaleY":2.99},{"id":"1","position":{"x":193,"y":-1696.3161653996626},"scaleX":2.96,"scaleY":2.99},{"id":"1","position":{"x":0,"y":-1372.3161653996626},"scaleX":1.72,"scaleY":1.74},{"id":"1","position":{"x":-277,"y":-1400.3161653996626},"scaleX":2.96,"scaleY":2.99},{"id":"1","position":{"x":-325,"y":-1988.4861753119694},"scaleX":-1.37,"scaleY":1.37},{"id":"1","position":{"x":-220,"y":-2058.4861753119694},"scaleX":-1.37,"scaleY":1.37},{"id":"1","position":{"x":-115,"y":-2127.4861753119694},"scaleX":-1.37,"scaleY":1.37},{"id":"1","position":{"x":-10,"y":-2197.4861753119694},"scaleX":-1.37,"scaleY":1.37},{"id":"1","position":{"x":94,"y":-2267.4861753119694},"scaleX":-1.37,"scaleY":1.37},{"id":"1","position":{"x":199,"y":-2336.4861753119694},"scaleX":-1.37,"scaleY":1.37},{"id":"1","position":{"x":304,"y":-2406.4861753119694},"scaleX":-1.37,"scaleY":1.37},{"id":"1","position":{"x":198,"y":-2465.4861753119694},"scaleX":-1.37,"scaleY":1.37},{"id":"1","position":{"x":93,"y":-2523.4861753119694},"scaleX":-1.37,"scaleY":1.37},{"id":"1","position":{"x":-13,"y":-2582.4861753119694},"scaleX":-1.37,"scaleY":1.37},{"id":"1","position":{"x":-118,"y":-2640.4861753119694},"scaleX":-1.37,"scaleY":1.37},{"id":"1","position":{"x":-224,"y":-2699.4861753119694},"scaleX":-1.37,"scaleY":1.37},{"id":"1","position":{"x":-329,"y":-2757.4861753119694},"scaleX":-1.37,"scaleY":1.37},{"id":"1","position":{"x":139,"y":-3328.811622341895},"scaleX":-0.61,"scaleY":0.61},{"id":"1","position":{"x":-48,"y":-3346.811622341895},"scaleX":-0.61,"scaleY":0.61},{"id":"1","position":{"x":90,"y":-3141.811622341895},"scaleX":-0.61,"scaleY":0.61},{"id":"1","position":{"x":2,"y":-286.6455429366135},"scaleX":-0.64,"scaleY":0.64},{"id":"1","position":{"x":46,"y":-239.64554293661348},"scaleX":-1},{"checkWithBoom":false,"id":"2","position":{"x":305,"y":-1249.3161653996626},"rotation":-45,"width":200},{"checkWithBoom":false,"id":"2","position":{"x":-305,"y":-803.3161653996627},"rotation":45,"width":200},{"checkWithBoom":false,"id":"2","position":{"x":-129,"y":-2241.4861753119694},"rotation":30,"scaleX":-1,"width":600},{"checkWithBoom":false,"id":"2","position":{"x":-8,"y":-3174.811622341895},"rotation":-55,"scaleX":-1,"width":700},{"checkWithBoom":false,"id":"2","position":{"x":201,"y":-3349.811622341895},"rotation":-55,"scaleX":-1,"width":700},{"checkWithBoom":true,"id":"2","position":{"x":-229,"y":-3627.811622341895},"scaleX":-1,"width":500},{"checkWithBoom":true,"id":"2","position":{"x":-336,"y":-3473.811622341895},"scaleX":-1,"width":300},{"checkWithBoom":false,"id":"2","position":{"x":262,"y":-4752.747105334525},"rotation":-5,"width":200},{"checkWithBoom":false,"id":"2","position":{"x":-174,"y":-4473.747105334525},"rotation":70,"width":350},{"checkWithBoom":false,"id":"2","position":{"x":-113,"y":-4748.747105334525},"rotation":5,"width":300},{"checkWithBoom":true,"id":"2","position":{"x":90,"y":-6552.594240988723},"rotation":90,"width":500},{"checkWithBoom":true,"id":"2","position":{"x":-90,"y":-6552.594240988723},"rotation":90,"width":500},{"checkWithBoom":true,"id":"2","position":{"x":37,"y":-6342.594240988723},"rotation":-45,"width":130},{"checkWithBoom":true,"id":"2","position":{"x":-37,"y":-6342.594240988723},"rotation":45,"width":130},{"checkWithBoom":false,"id":"2","position":{"x":113,"y":-7387.664462650539},"rotation":70,"width":250},{"checkWithBoom":false,"id":"2","position":{"x":-113,"y":-7387.664462650539},"rotation":-70,"width":250},{"checkWithBoom":false,"id":"2","position":{"x":-305,"y":-1249.3161653996626},"rotation":45,"width":200},{"checkWithBoom":false,"id":"2","position":{"x":305,"y":-803.3161653996627},"rotation":-45,"width":200},{"clockwise":true,"height":257,"id":"15","position":{"x":284,"y":-3015.811622341895},"scaleX":-0.44,"scaleY":0.44,"speed":450,"width":247},{"clockwise":true,"height":257,"id":"15","position":{"x":-20,"y":-3453.811622341895},"scaleX":-0.44,"scaleY":0.44,"speed":450,"width":247},{"clockwise":false,"height":257,"id":"15","position":{"x":56,"y":-3344.811622341895},"scaleX":-0.44,"scaleY":0.44,"speed":450,"width":247},{"clockwise":true,"height":257,"id":"15","position":{"x":132,"y":-3234.811622341895},"scaleX":-0.44,"scaleY":0.44,"speed":450,"width":247},{"clockwise":false,"height":257,"id":"15","position":{"x":208,"y":-3125.811622341895},"scaleX":-0.44,"scaleY":0.44,"speed":450,"width":247},{"clockwise":false,"height":257,"id":"15","position":{"x":1,"y":-5797.13664447087},"scaleX":-1.31,"scaleY":1.31,"speed":250,"width":247},{"clockwise":true,"height":257,"id":"15","position":{"x":160,"y":-1080.3161653996626},"scaleX":1.29,"scaleY":1.29,"speed":250,"width":247},{"clockwise":false,"height":257,"id":"15","position":{"x":-160,"y":-1080.3161653996626},"scaleX":1.29,"scaleY":1.29,"speed":250,"width":247},{"height":114.7,"id":"12","position":{"x":-7,"y":-3956.476105310092},"scaleX":1.64,"scaleY":1.64,"width":114.2},{"height":114.7,"id":"12","position":{"x":0,"y":-7263.664462650539},"width":114.2},{"id":"7","position":{"x":130,"y":-4507.747105334525}},{"id":"7","position":{"x":230,"y":-4572.747105334525}},{"id":"7","position":{"x":230,"y":-4459.747105334525}},{"id":"7","position":{"x":17,"y":-4459.747105334525}},{"id":"7","position":{"x":17,"y":-4572.747105334525}},{"id":"3","position":{"x":-259,"y":-7029.664462650539}},{"id":"3","position":{"x":259,"y":-7029.664462650539},"scaleX":-1},{"id":"3","position":{"x":-87,"y":-5164.13664447087},"rotation":-15,"scaleX":-1},{"id":"3","position":{"x":96,"y":-5166.13664447087},"rotation":15},{"id":"9","position":{"x":-281,"y":-3561.811622341895},"scaleX":-1},{"id":"9","position":{"x":-2,"y":-6264.594240988723}}],"lines":[[{"pos":{"x":0,"y":-236.64554293661348},"radius":90},{"pos":{"x":0,"y":-526.6455429366135},"radius":90}],[{"pos":{"x":-360,"y":-1317.3161653996626},"radius":450},{"pos":{"x":360,"y":-1317.3161653996626},"radius":450}],[{"pos":{"x":-1,"y":-1686.3161653996626},"radius":200}],[{"pos":{"x":318,"y":-2991.811622341895},"radius":120},{"pos":{"x":-35,"y":-3470.811622341895},"radius":120}],[{"pos":{"x":-5,"y":-3964.476105310092},"radius":250}],[{"pos":{"x":0,"y":-6147.594240988723},"radius":100},{"pos":{"x":0,"y":-6800.594240988723},"radius":100}]],"staticBalls":[],"bigBalls":[]}