{"lv":472,"height":5842.937591320687,"needBalls":20,"originHoles":[{"num":"10","radius":100,"x":0}],"holes":[{"num":"10","pos":{"x":0,"y":-205},"radius":80},{"num":"10","pos":{"x":-175,"y":-2793.3289850929364},"radius":100}],"obstacles":[{"id":"1","position":{"x":115,"y":-1094.78240595942},"scaleX":-2,"scaleY":2},{"checkWithBoom":false,"id":"2","position":{"x":99,"y":-677.78240595942},"rotation":20,"scaleX":-1,"width":250},{"checkWithBoom":false,"id":"2","position":{"x":-116,"y":-677.78240595942},"rotation":-20,"scaleX":-1,"width":250},{"checkWithBoom":false,"id":"2","position":{"x":120,"y":-1300.78240595942},"rotation":20,"scaleX":-1,"width":250},{"checkWithBoom":false,"id":"2","position":{"x":-95,"y":-1300.78240595942},"rotation":-20,"scaleX":-1,"width":250},{"checkWithBoom":false,"id":"2","position":{"x":259,"y":-853.78240595942},"rotation":-20,"scaleX":-1,"width":250},{"checkWithBoom":false,"id":"2","position":{"x":-283,"y":-853.78240595942},"rotation":20,"scaleX":-1,"width":250},{"checkWithBoom":false,"id":"2","position":{"x":-241,"y":-1501.78240595942},"rotation":60,"scaleX":-1,"width":500},{"checkWithBoom":false,"id":"2","position":{"x":245,"y":-1497.78240595942},"rotation":-60,"scaleX":-1,"width":500},{"id":"1","position":{"x":-115,"y":-1094.78240595942},"scaleX":-2,"scaleY":2},{"id":"7","position":{"x":-219,"y":-2110.6460154828947}},{"id":"1","position":{"x":-133,"y":-1889.6460154828944}},{"id":"1","position":{"x":209,"y":-2305.6460154828947}},{"id":"1","position":{"x":-209,"y":-2305.6460154828947}},{"id":"1","position":{"x":3,"y":-2204.6460154828947}},{"id":"1","position":{"x":-110,"y":-2142.6460154828947}},{"id":"1","position":{"x":110,"y":-2142.6460154828947}},{"id":"1","position":{"x":106,"y":-2037.6460154828944}},{"id":"1","position":{"x":-106,"y":-2037.6460154828944}},{"id":"1","position":{"x":-213,"y":-1990.6460154828944}},{"id":"1","position":{"x":213,"y":-1990.6460154828944}},{"id":"1","position":{"x":-3,"y":-1990.6460154828944}},{"id":"1","position":{"x":133,"y":-1889.6460154828944}},{"checkWithBoom":false,"id":"2","position":{"x":-1,"y":-2096.6460154828947},"rotation":1,"width":100},{"checkWithBoom":false,"id":"2","position":{"x":-102,"y":-2242.6460154828947},"rotation":1,"width":100},{"checkWithBoom":false,"id":"2","position":{"x":102,"y":-2242.6460154828947},"rotation":-1,"width":100},{"id":"7","position":{"x":219,"y":-2222.6460154828947}},{"id":"7","position":{"x":219,"y":-2110.6460154828947}},{"id":"7","position":{"x":-219,"y":-2222.6460154828947}},{"id":"14","position":{"x":71,"y":-2991.3289850929364},"rotation":-24,"scaleX":-0.5,"scaleY":0.5},{"id":"14","position":{"x":186,"y":-2940.3289850929364},"rotation":-24,"scaleX":-0.5,"scaleY":0.5},{"id":"14","position":{"x":134,"y":-2963.3289850929364},"rotation":-24,"scaleX":-0.5,"scaleY":0.5},{"id":"14","position":{"x":257,"y":-2909.3289850929364},"rotation":-24,"scaleX":-0.5,"scaleY":0.5},{"height":114.7,"id":"12","position":{"x":-47,"y":-4370.879323711671},"scaleX":1.42,"scaleY":1.42,"width":114.2},{"checkWithBoom":false,"id":"2","position":{"x":224,"y":-3489.8793237116706},"rotation":-40,"width":350},{"id":"1","position":{"x":42,"y":-3493.8793237116706},"scaleX":1.49,"scaleY":1.49},{"checkWithBoom":false,"id":"2","position":{"x":-222,"y":-4116.879323711671},"rotation":40,"width":350},{"checkWithBoom":false,"id":"2","position":{"x":243,"y":-4655.879323711671},"rotation":-40,"width":350},{"id":"1","position":{"x":154,"y":-3405.8793237116706},"scaleX":1.49,"scaleY":1.49},{"id":"1","position":{"x":173,"y":-4571.879323711671},"scaleX":1.49,"scaleY":1.49},{"id":"1","position":{"x":284,"y":-4482.879323711671},"scaleX":1.49,"scaleY":1.49},{"id":"1","position":{"x":-271,"y":-3954.8793237116706},"scaleX":1.49,"scaleY":1.49},{"id":"1","position":{"x":-159,"y":-4043.8793237116706},"scaleX":1.49,"scaleY":1.49},{"id":"1","position":{"x":-48,"y":-4131.879323711671},"scaleX":1.49,"scaleY":1.49},{"id":"1","position":{"x":265,"y":-3316.8793237116706},"scaleX":1.49,"scaleY":1.49},{"height":114.7,"id":"12","position":{"x":18,"y":-4875.879323711671},"scaleX":1.42,"scaleY":1.42,"width":114.2},{"height":114.7,"id":"12","position":{"x":16,"y":-3718.8793237116706},"scaleX":1.42,"scaleY":1.42,"width":114.2},{"id":"14","position":{"x":55,"y":-5427.937591320687},"scaleX":0.36,"scaleY":0.36},{"checkWithBoom":false,"id":"2","position":{"x":-98,"y":-5154.937591320687},"rotation":-30,"width":250},{"checkWithBoom":false,"id":"2","position":{"x":92,"y":-5152.937591320687},"rotation":30,"width":250},{"checkWithBoom":false,"id":"2","position":{"x":0,"y":-5460.937591320687},"width":300},{"id":"14","position":{"x":-112,"y":-5427.937591320687},"scaleX":0.36,"scaleY":0.36},{"id":"14","position":{"x":0,"y":-5427.937591320687},"scaleX":0.36,"scaleY":0.36},{"id":"14","position":{"x":111,"y":-5427.937591320687},"scaleX":0.36,"scaleY":0.36},{"id":"14","position":{"x":-56,"y":-5427.937591320687},"scaleX":0.36,"scaleY":0.36},{"id":"17","position":{"x":-60.584793886504116,"y":-5618.506981393087}}],"lines":[[{"pos":{"x":360,"y":-1093.78240595942},"radius":700},{"pos":{"x":-360,"y":-1093.78240595942},"radius":700}],[{"pos":{"x":-114,"y":-2124.6460154828947},"radius":250},{"pos":{"x":115,"y":-2124.6460154828947},"radius":250}],[{"pos":{"x":-360,"y":-2513.3289850929364},"radius":60},{"pos":{"x":360,"y":-2822.328985092936},"radius":60},{"pos":{"x":-360,"y":-3131.328985092936},"radius":60}]],"staticBalls":[],"bigBalls":[]}