{"lv":489,"height":5332.6768096665255,"needBalls":20,"originHoles":[{"num":"10","radius":80,"x":0}],"holes":[{"num":"0","pos":{"x":-153,"y":-302.1687422223514},"radius":150},{"num":"0","pos":{"x":153,"y":-302.1687422223514},"radius":150},{"num":"10","pos":{"x":-182,"y":-2268.8771165636363},"radius":80},{"num":"10","pos":{"x":-133.85937537716535,"y":-2770.0956939701987},"radius":90}],"obstacles":[{"clockwise":true,"height":257,"id":"15","position":{"x":-156,"y":-300.1687422223514},"speed":200,"width":247},{"clockwise":false,"height":257,"id":"15","position":{"x":153,"y":-300.1687422223514},"speed":200,"width":247},{"id":"11","position":{"x":-360,"y":-696.3296641915965},"scaleX":1.21,"scaleY":1.21},{"id":"11","position":{"x":0,"y":-696.3296641915965},"scaleX":1.21,"scaleY":1.21},{"id":"11","position":{"x":360,"y":-696.3296641915965},"scaleX":1.21,"scaleY":1.21},{"id":"11","position":{"x":-183,"y":-957.3296641915965},"scaleX":1.21,"scaleY":1.21},{"id":"11","position":{"x":183,"y":-957.3296641915965},"scaleX":1.21,"scaleY":1.21},{"id":"11","position":{"x":-360,"y":-1218.3296641915965},"scaleX":1.21,"scaleY":1.21},{"id":"11","position":{"x":0,"y":-1218.3296641915965},"scaleX":1.21,"scaleY":1.21},{"id":"11","position":{"x":360,"y":-1218.3296641915965},"scaleX":1.21,"scaleY":1.21},{"id":"11","position":{"x":-183,"y":-1462.3296641915965},"scaleX":1.21,"scaleY":1.21},{"id":"11","position":{"x":183,"y":-1462.3296641915965},"scaleX":1.21,"scaleY":1.21},{"id":"11","position":{"x":0,"y":-1671.3296641915965},"scaleX":1.21,"scaleY":1.21},{"height":114.7,"id":"12","position":{"x":168,"y":-2282.8771165636363},"scaleX":-1.2,"scaleY":1.2,"width":114.2},{"checkWithBoom":false,"id":"2","position":{"x":-213,"y":-2018.8771165636363},"rotation":-30,"scaleX":-1,"width":350},{"checkWithBoom":false,"id":"2","position":{"x":218,"y":-2059.8771165636363},"rotation":-30,"scaleX":-1,"width":350},{"checkWithBoom":false,"id":"2","position":{"x":206,"y":-2514.8771165636363},"rotation":30,"scaleX":-1,"width":350},{"checkWithBoom":false,"id":"2","position":{"x":-212,"y":-2514.8771165636363},"rotation":30,"scaleX":-1,"width":350},{"checkWithBoom":false,"id":"2","position":{"x":-69,"y":-3123.293901526246},"rotation":-90,"scaleX":-1,"width":250},{"checkWithBoom":false,"id":"2","position":{"x":-213,"y":-3123.293901526246},"rotation":-90,"scaleX":-1,"width":250},{"checkWithBoom":false,"id":"2","position":{"x":-135,"y":-3769.293901526246},"rotation":-90,"scaleX":-1,"width":250},{"checkWithBoom":false,"id":"2","position":{"x":9,"y":-3769.293901526246},"rotation":-90,"scaleX":-1,"width":250},{"checkWithBoom":false,"id":"2","position":{"x":87,"y":-3435.293901526246},"rotation":-90,"scaleX":-1,"width":250},{"checkWithBoom":false,"id":"2","position":{"x":231,"y":-3435.293901526246},"rotation":-90,"scaleX":-1,"width":250},{"id":"1","position":{"x":-98,"y":-3446.293901526246},"scaleX":-1},{"id":"1","position":{"x":169,"y":-3777.293901526246},"scaleX":-1},{"id":"1","position":{"x":-206,"y":-4685.6768096665255}},{"checkWithBoom":false,"id":"2","position":{"x":-131,"y":-4251.6768096665255},"rotation":60,"width":350},{"checkWithBoom":false,"id":"2","position":{"x":-131,"y":-4251.6768096665255},"rotation":-50,"width":350},{"checkWithBoom":false,"id":"2","position":{"x":-131,"y":-4251.6768096665255},"width":350},{"checkWithBoom":false,"id":"2","position":{"x":174,"y":-4779.6768096665255},"rotation":60,"width":350},{"checkWithBoom":false,"id":"2","position":{"x":174,"y":-4779.6768096665255},"width":350},{"checkWithBoom":false,"id":"2","position":{"x":174,"y":-4779.6768096665255},"rotation":-50,"width":350},{"id":"1","position":{"x":-98,"y":-4947.6768096665255}},{"id":"17","position":{"x":262.11172366241243,"y":-5090.16909566717}}],"lines":[[{"pos":{"x":-5,"y":-1316.3296641915965},"radius":500}],[{"pos":{"x":-360,"y":-1098.3296641915965},"radius":550},{"pos":{"x":360,"y":-1098.3296641915965},"radius":550}]],"staticBalls":[],"bigBalls":[]}